[
  {
    "src": "assets/img/memorial/01.jpg",
    "alt": "Foto do acervo Laia Music",
    "credit": "Arquivo familiar"
  },
  {
    "src": "assets/img/memorial/02.jpg",
    "alt": "Foto do acervo Laia Music",
    "credit": "Arquivo familiar"
  },
  {
    "src": "assets/img/memorial/03.jpg",
    "alt": "Foto do acervo Laia Music",
    "credit": "Arquivo familiar"
  },
  {
    "src": "assets/img/memorial/04.jpg",
    "alt": "Foto do acervo Laia Music",
    "credit": "Arquivo familiar"
  },
  {
    "src": "assets/img/memorial/05.jpg",
    "alt": "Foto do acervo Laia Music",
    "credit": "Arquivo familiar"
  },
  {
    "src": "assets/img/memorial/06.jpg",
    "alt": "Foto do acervo Laia Music",
    "credit": "Arquivo familiar"
  },
  {
    "src": "assets/img/memorial/07.jpg",
    "alt": "Foto do acervo Laia Music",
    "credit": "Arquivo familiar"
  },
  {
    "src": "assets/img/memorial/08.jpg",
    "alt": "Foto do acervo Laia Music",
    "credit": "Arquivo familiar"
  },
  {
    "src": "assets/img/memorial/09.jpg",
    "alt": "Foto do acervo Laia Music",
    "credit": "Arquivo familiar"
  },
  {
    "src": "assets/img/memorial/10.jpg",
    "alt": "Foto do acervo Laia Music",
    "credit": "Arquivo familiar"
  },
  {
    "src": "assets/img/memorial/11.jpg",
    "alt": "Foto do acervo Laia Music",
    "credit": "Arquivo familiar"
  },
  {
    "src": "assets/img/memorial/12.jpg",
    "alt": "Foto do acervo Laia Music",
    "credit": "Arquivo familiar"
  },
  {
    "src": "assets/img/memorial/13.jpg",
    "alt": "Foto do acervo Laia Music",
    "credit": "Arquivo familiar"
  },
  {
    "src": "assets/img/memorial/14.jpg",
    "alt": "Foto do acervo Laia Music",
    "credit": "Arquivo familiar"
  },
  {
    "src": "assets/img/memorial/15.jpg",
    "alt": "Foto do acervo Laia Music",
    "credit": "Arquivo familiar"
  },
  {
    "src": "assets/img/memorial/16.jpg",
    "alt": "Foto do acervo Laia Music",
    "credit": "Arquivo familiar"
  },
  {
    "src": "assets/img/memorial/17.jpg",
    "alt": "Foto do acervo Laia Music",
    "credit": "Arquivo familiar"
  },
  {
    "src": "assets/img/memorial/18.jpg",
    "alt": "Foto do acervo Laia Music",
    "credit": "Arquivo familiar"
  },
  {
    "src": "assets/img/memorial/19.jpg",
    "alt": "Foto do acervo Laia Music",
    "credit": "Arquivo familiar"
  },
  {
    "src": "assets/img/memorial/20.jpg",
    "alt": "Foto do acervo Laia Music",
    "credit": "Arquivo familiar"
  },
  {
    "src": "assets/img/memorial/21.jpg",
    "alt": "Foto do acervo Laia Music",
    "credit": "Arquivo familiar"
  },
  {
    "src": "assets/img/memorial/22.jpg",
    "alt": "Foto do acervo Laia Music",
    "credit": "Arquivo familiar"
  },
  {
    "src": "assets/img/memorial/23.jpg",
    "alt": "Foto do acervo Laia Music",
    "credit": "Arquivo familiar"
  },
  {
    "src": "assets/img/memorial/24.jpg",
    "alt": "Foto do acervo Laia Music",
    "credit": "Arquivo familiar"
  },
  {
    "src": "assets/img/memorial/25.jpg",
    "alt": "Foto do acervo Laia Music",
    "credit": "Arquivo familiar"
  }
]